{
  "required": true,
  "minVersion": "0.8",
  "package": "yolojj333.ethanserver.mixin",
  "compatibilityLevel": "JAVA_17",
  "mixins": [
    "enchantment.ExperienceOrbEntityMixin",
    "enchantment.InfinityEnchantmentMixin",
    "enchantment.MultishotEnchantmentMixin",
    "enchantment.PiercingEnchantmentMixin",
    "entity.MerchantEntityMixin",
    "item.GoatHornItemMixin",
    "recipe.FireworkRocketRecipeMixin"
  ],
  "server": [
    "server.command.BanCommandMixin",
    "server.command.PardonCommandMixin",
    "server.command.WhitelistCommandMixin"
  ],
  "client": [
  ],
  "injectors": {
    "defaultRequire": 1
  }
}